cocktail_info/__init__.py
cocktail_info/cocktail_info.py
cocktail_info-0.1.8.dist-info/LICENSE
cocktail_info-0.1.8.dist-info/WHEEL
cocktail_info-0.1.8.dist-info/METADATA
cocktail_info-0.1.8.dist-info/RECORD
