Metadata-Version: 2.1
Name: cocktail-info
Version: 0.1.8
Summary: Get the information of cocktails.
Home-page: https://github.com/Kenyaokun/cocktail_info
License: MIT
Author: Kun Yao
Requires-Python: >=3.9,<4.0
Classifier: License :: OSI Approved :: MIT License
Classifier: Programming Language :: Python :: 3
Classifier: Programming Language :: Python :: 3.10
Classifier: Programming Language :: Python :: 3.9
Requires-Dist: ipython (==7.29.0)
Requires-Dist: pandas (==1.3.4)
Requires-Dist: requests (>=2.26.0,<3.0.0)
Project-URL: Documentation, https://cocktail_info.readthedocs.io
Project-URL: Repository, https://github.com/Kenyaokun/cocktail_info
